tunqi/__init__.py
tunqi/audit.py
tunqi/core/__init__.py
tunqi/core/column.py
tunqi/core/condition.py
tunqi/core/database.py
tunqi/core/expression.py
tunqi/core/functions_.py
tunqi/core/join.py
tunqi/core/migration.py
tunqi/core/query.py
tunqi/core/selector.py
tunqi/core/table.py
tunqi/debug.py
tunqi/errors.py
tunqi/orm/__init__.py
tunqi/orm/annotations.py
tunqi/orm/backref.py
tunqi/orm/fk.py
tunqi/orm/m2m.py
tunqi/orm/model.py
tunqi/orm/model_type.py
tunqi/py.typed
tunqi/sync/__init__.py
tunqi/sync/backref.py
tunqi/sync/database.py
tunqi/sync/fk.py
tunqi/sync/m2m.py
tunqi/sync/model.py
tunqi/sync/model_type.py
tunqi/utils.py
tunqi-0.1.2.dist-info/LICENSE
tunqi-0.1.2.dist-info/METADATA
tunqi-0.1.2.dist-info/WHEEL
tunqi-0.1.2.dist-info/RECORD
