Metadata-Version: 2.3
Name: tunqi
Version: 0.1.2
Summary: A convenient and extendable ORM for Python.
Author: Dan Gittik
Author-email: dan.gittik@gmail.com
Requires-Python: >=3.12
Classifier: Programming Language :: Python :: 3
Classifier: Programming Language :: Python :: 3.12
Classifier: Programming Language :: Python :: 3.13
Provides-Extra: all
Provides-Extra: debug
Provides-Extra: mysql
Provides-Extra: postgresql
Provides-Extra: sqlite
Requires-Dist: aiomysql (>=0.2.0,<1.0.0) ; extra == "all"
Requires-Dist: aiomysql (>=0.2.0,<1.0.0) ; extra == "mysql"
Requires-Dist: aiosqlite (>=0.21.0,<1.0.0) ; extra == "all"
Requires-Dist: aiosqlite (>=0.21.0,<1.0.0) ; extra == "sqlite"
Requires-Dist: alembic (>=1.16.2,<2.0.0)
Requires-Dist: asyncpg (>=0.30.0,<1.0.0) ; extra == "all"
Requires-Dist: asyncpg (>=0.30.0,<1.0.0) ; extra == "postgresql"
Requires-Dist: inflect (>=7.5.0,<8.0.0)
Requires-Dist: psycopg2 (>=2.9.10,<3.0.0) ; extra == "all"
Requires-Dist: psycopg2 (>=2.9.10,<3.0.0) ; extra == "postgresql"
Requires-Dist: pydantic (>=2.11.7,<3.0.0)
Requires-Dist: pymysql (>=1.1.1,<2) ; extra == "all"
Requires-Dist: pymysql (>=1.1.1,<2) ; extra == "mysql"
Requires-Dist: rich (>=14.0.0,<15) ; extra == "debug"
Requires-Dist: sqlalchemy[asyncio] (>=2.0.41,<3.0.0)
Requires-Dist: sqlparse (>=0.5.3,<0.6.0)
Requires-Dist: srlz (>=0.1.0,<0.2.0)
